dal_docx_creator/__init__.py
dal_docx_creator/converter.py
dal_docx_creator/creator.py
dal_docx_creator/example/__init__.py
dal_docx_creator-0.0.7.dist-info/LICENSE
dal_docx_creator-0.0.7.dist-info/METADATA
dal_docx_creator-0.0.7.dist-info/WHEEL
dal_docx_creator-0.0.7.dist-info/top_level.txt
dal_docx_creator-0.0.7.dist-info/RECORD
