Metadata-Version: 2.1
Name: dal-docx-creator
Version: 0.0.7
Summary: DOCX Creator
Home-page: UNKNOWN
Author: Daniel Alcalá
Author-email: <danielalcalavalera@gmail.com>
License: UNKNOWN
Keywords: docx creator
Platform: UNKNOWN
Classifier: Development Status :: 3 - Alpha
Classifier: Intended Audience :: Education
Classifier: Programming Language :: Python :: 2
Classifier: Programming Language :: Python :: 3
Classifier: Operating System :: MacOS :: MacOS X
Classifier: Operating System :: Microsoft :: Windows
Requires-Dist: python-docx
Requires-Dist: comtypes
Requires-Dist: yta-general-utils
